pytest_httpchain/__init__.py
pytest_httpchain/carrier.py
pytest_httpchain/constants.py
pytest_httpchain/exceptions.py
pytest_httpchain/plugin.py
pytest_httpchain/report_formatter.py
pytest_httpchain/utils.py
pytest_httpchain-0.2.1.dist-info/licenses/LICENSE
pytest_httpchain-0.2.1.dist-info/WHEEL
pytest_httpchain-0.2.1.dist-info/entry_points.txt
pytest_httpchain-0.2.1.dist-info/METADATA
pytest_httpchain-0.2.1.dist-info/RECORD
