Metadata-Version: 2.4
Name: pytest-httpchain
Version: 0.2.1
Summary: pytest plugin for HTTP testing using JSON files
Keywords: testing,pytest,requests
Author: Alexander Eresov
Author-email: Alexander Eresov <aeresov@gmail.com>
License-Expression: MIT
License-File: LICENSE
Classifier: Development Status :: 5 - Production/Stable
Classifier: Framework :: Pytest
Classifier: Intended Audience :: Developers
Classifier: License :: OSI Approved :: MIT License
Classifier: Programming Language :: Python :: 3
Classifier: Programming Language :: Python :: 3.13
Classifier: Topic :: Software Development :: Testing
Requires-Dist: httpx[http2]>=0.27.0
Requires-Dist: pydantic>=2.11.7
Requires-Dist: pyrate-limiter>=3.0.0
Requires-Dist: pytest-httpchain-jsonref
Requires-Dist: pytest-httpchain-models
Requires-Dist: pytest-order>=1.3.0
Requires-Dist: pytest-httpchain-mcp ; extra == 'mcp'
Requires-Python: >=3.13, <4.0
Provides-Extra: mcp
